{
  "sentences": [
    { "number": 1, "parts": ["Banks usually require the consent of all parties before closing a ", { "slot": "gapfill-q1", "answers": ["joint account"] }, ", since either holder could otherwise be left without access to shared funds."] },
    { "number": 2, "parts": ["A sudden fall on the ", { "slot": "gapfill-q2", "answers": ["stock market"] }, " can wipe out a large part of the value of pension funds in a single day."] },
    { "number": 3, "parts": ["Unable to raise enough capital from shareholders, the founders had to ", { "slot": "gapfill-q3", "answers": ["borrow"] }, " from a specialist lender."] },
    { "number": 4, "parts": ["The factory blamed rising ", { "slot": "gapfill-q4", "answers": ["commodities"] }, " prices, especially for oil and steel, for its declining profit margins."] },
    { "number": 5, "parts": ["Before approving the takeover, the board asked for an independent ", { "slot": "gapfill-q5", "answers": ["financial"] }, " review of the target company's accounts."] },
    { "number": 6, "parts": ["After three quarters of falling output and rising unemployment, the country was widely described as being in a ", { "slot": "gapfill-q6", "answers": ["recession"] }, "."] },
    { "number": 7, "parts": ["The bank allowed a temporary ", { "slot": "gapfill-q7", "answers": ["overdraft"] }, " so the business could pay suppliers while waiting for customer invoices."] },
    { "number": 8, "parts": ["A patient ", { "slot": "gapfill-q8", "answers": ["investor"] }, " may accept lower short-term returns in exchange for steady long-term growth."] },
    { "number": 9, "parts": ["If you only pay the minimum amount on your ", { "slot": "gapfill-q9", "answers": ["credit card"] }, " each month, your debt can grow quickly because of interest charges."] },
    { "number": 10, "parts": ["The agreement was expected to boost cross-border ", { "slot": "gapfill-q10", "answers": ["trade"] }, " in services as well as manufactured goods."] },
    { "number": 11, "parts": ["For day-to-day spending, she kept her money in a ", { "slot": "gapfill-q11", "answers": ["current account"] }, " rather than in fixed-term deposits or a shared household account."] },
    { "number": 12, "parts": ["She shopped around carefully because even a small difference in the ", { "slot": "gapfill-q12", "answers": ["interest"] }, " rate could save thousands over the life of a mortgage."] },
    { "number": 13, "parts": ["The insurance ", { "slot": "gapfill-q13", "answers": ["broker"] }, " compared policies from several providers and recommended the best-value option."] },
    { "number": 14, "parts": ["Slower ", { "slot": "gapfill-q14", "answers": ["economic"] }, " growth forced the government to revise its public spending plans for the coming year."] },
    { "number": 15, "parts": ["Rather than investing the money, they decided to build up their ", { "slot": "gapfill-q15", "answers": ["savings"] }, " for unforeseen expenses."] },
    { "number": 16, "parts": ["Exporters benefited when the national ", { "slot": "gapfill-q16", "answers": ["currency"] }, " weakened, because their goods became cheaper for foreign buyers."] },
    { "number": 17, "parts": ["To buy the van, she took out a small business ", { "slot": "gapfill-q17", "answers": ["loan"] }, " and agreed to repay it in monthly instalments."] },
    { "number": 18, "parts": ["The app alerts customers when their account ", { "slot": "gapfill-q18", "answers": ["balance"] }, " falls below £100."] },
    { "number": 19, "parts": ["On the exchange floor, a ", { "slot": "gapfill-q19", "answers": ["trader"] }, " may buy and sell the same commodity several times in one session."] },
    { "number": 20, "parts": ["For the fifth year running, government spending exceeded tax revenue, leaving a significant budget ", { "slot": "gapfill-q20", "answers": ["deficit"] }, "."] }
  ]
}
